reportomatic/__init__.py
reportomatic/__main__.py
reportomatic/client.py
reportomatic/adapters/__init__.py
reportomatic/adapters/base.py
reportomatic/adapters/github.py
reportomatic/adapters/gitlab.py
reportomatic/adapters/helpers.py
reportomatic/adapters/objects.py
reportomatic/adapters/states.py
reportomatic-0.2.7.dist-info/METADATA
reportomatic-0.2.7.dist-info/WHEEL
reportomatic-0.2.7.dist-info/entry_points.txt
reportomatic-0.2.7.dist-info/top_level.txt
reportomatic-0.2.7.dist-info/RECORD
