Metadata-Version: 2.4
Name: reportomatic
Version: 0.2.7
Summary: Reportomatic automates Markdown report generation from GitLab and GitHub repositories.
Author-email: Leo Turnell-Ritson <l.n.turnell-ritson@bham.ac.uk>
License-Expression: MIT
Project-URL: Repository, https://github.com/LeoTurnell-Ritson/reportomatic
Requires-Python: >=3.9
Requires-Dist: click
Requires-Dist: python-gitlab
Requires-Dist: PyGithub
Provides-Extra: lint
Requires-Dist: ruff; extra == "lint"
Provides-Extra: test
Requires-Dist: nose2[coverage_plugin]; extra == "test"
